{
  "bug_list": "",
  "bug_search_url": "",
  "channel": "Release",
  "created": "2024-03-04T12:28:53.582433+00:00",
  "is_public": true,
  "modified": "2024-03-05T13:12:20.915573+00:00",
  "notes": [
    {
      "bug": null,
      "created": "2024-03-04T12:30:35.337009+00:00",
      "id": 790021,
      "is_public": true,
      "modified": "2024-03-04T12:30:35.336823+00:00",
      "note": "Reference link to [123.0 release notes][1]\r\n\t\r\n\r\n\r\n  [1]: https://www.mozilla.org/firefox/123.0/releasenotes/",
      "progressive_rollout": false,
      "relevant_countries": [],
      "sort_num": 0,
      "tag": ""
    },
    {
      "bug": 1879415,
      "created": "2024-03-04T12:55:22.262706+00:00",
      "id": 790022,
      "is_public": true,
      "modified": "2024-03-04T14:00:58.367477+00:00",
      "note": "Fixed the *Firefox Translation* language indicator in the address bar displaying a colored square icon instead of the language code icon. ([Bug 1879415][1])\r\n\r\n\r\n  [1]: https://bugzilla.mozilla.org/show_bug.cgi?id=1879415",
      "progressive_rollout": false,
      "relevant_countries": [],
      "sort_num": 0,
      "tag": "Fixed"
    },
    {
      "bug": 1851963,
      "created": "2024-03-04T13:02:58.667225+00:00",
      "id": 790023,
      "is_public": true,
      "modified": "2024-03-04T14:00:41.206939+00:00",
      "note": "Fixed incorrect rendering of Canvas2D conic gradients colors on Windows. ([Bug 1851963][1])\r\n\r\n\r\n  [1]: https://bugzilla.mozilla.org/show_bug.cgi?id=1851963",
      "progressive_rollout": false,
      "relevant_countries": [],
      "sort_num": 0,
      "tag": "Fixed"
    },
    {
      "bug": 1881457,
      "created": "2024-03-04T13:36:37.144002+00:00",
      "id": 790024,
      "is_public": true,
      "modified": "2024-03-04T14:57:37.826056+00:00",
      "note": "Fixed a regression with the `onChange` event not firing when clearing the value of a `textarea` HTML field. ([Bug 1881457][1])\r\n\r\n\r\n  [1]: https://bugzilla.mozilla.org/show_bug.cgi?id=1881457",
      "progressive_rollout": false,
      "relevant_countries": [],
      "sort_num": 0,
      "tag": "Fixed"
    },
    {
      "bug": 1881830,
      "created": "2024-03-04T13:43:02.619157+00:00",
      "id": 790025,
      "is_public": true,
      "modified": "2024-03-04T13:43:02.618933+00:00",
      "note": "Fixed availability of system-level dictionaries for Linux users with Firefox installed as a Flatpak package. ([Bug 1881830][1])\r\n\r\n\r\n  [1]: https://bugzilla.mozilla.org/show_bug.cgi?id=1881830",
      "progressive_rollout": false,
      "relevant_countries": [],
      "sort_num": 0,
      "tag": "Fixed"
    },
    {
      "bug": 1882386,
      "created": "2024-03-04T13:52:30.113491+00:00",
      "id": 790026,
      "is_public": true,
      "modified": "2024-03-04T14:58:28.059292+00:00",
      "note": "Fixed a regression in the JavaScript JIT engine incorrectly  inlining strings in some cases. ([Bug 1882386][1])\r\n\r\n\r\n  [1]: https://bugzilla.mozilla.org/show_bug.cgi?id=1882386",
      "progressive_rollout": false,
      "relevant_countries": [],
      "sort_num": 0,
      "tag": "Fixed"
    },
    {
      "bug": 1877090,
      "created": "2024-03-04T13:57:05.380374+00:00",
      "id": 790027,
      "is_public": true,
      "modified": "2024-03-04T14:59:36.227580+00:00",
      "note": "Fixed low contrast of text when selecting rows in the Developer tools' Storage panel. ([Bug 1877090][1])\r\n\r\n\r\n  [1]: https://bugzilla.mozilla.org/show_bug.cgi?id=1877090",
      "progressive_rollout": false,
      "relevant_countries": [],
      "sort_num": 0,
      "tag": "Fixed"
    }
  ],
  "product": "Firefox",
  "release_date": "2024-03-05",
  "slug": "firefox-123.0.1-release",
  "system_requirements": "## Windows\r\n\r\n### Operating Systems (32-bit and 64-bit)\r\n - Windows 10 or later\r\n\r\n### Recommended Hardware\r\n-  1 gigahertz (GHz) or faster compatible processor or System on a Chip (SoC)\r\n-  1GB of RAM / 2GB of RAM for the 64-bit version\r\n-  500MB of hard drive space\r\n\r\n---\r\n\r\n## Mac\r\n\r\n### Operating Systems\r\n- macOS 10.15 or later\r\n\r\n### Recommended Hardware\r\n- Macintosh computer with an Intel x86 or Apple silicon processor\r\n- 512 MB of RAM\r\n- 200 MB hard drive space\r\n\r\n---\r\n\r\n## GNU/Linux\r\n\r\n### Software Requirements\r\n\r\n*Please note that GNU/Linux distributors may provide packages for your distribution which have different requirements.*\r\n\r\n- Firefox will not run at all without the following libraries or packages:\r\n    - glibc 2.17 or higher\r\n    - GTK+ 3.14 or higher\r\n    - libglib 2.42 or higher\r\n    - libstdc++ 4.8.1 or higher\r\n    - X.Org 1.0 or higher (1.7 or higher is recommended)\r\n- For optimal functionality, we recommend the following libraries or packages:\r\n    - DBus 1.0 or higher\r\n    - NetworkManager 0.7 or higher\r\n    - PulseAudio",
  "text": "",
  "title": "Firefox 123.0.1 Release",
  "version": "123.0.1"
}