{
  "product": "Firefox for Android",
  "bug_list": "",
  "title": "Firefox for Android 47.0 Release",
  "notes": [
    {
      "note": "Add \"Show/Hide web fonts\" in advanced settings to reduce bandwidth and data",
      "tag": "New",
      "is_public": true,
      "is_known_issue": false,
      "bug": 1249434
    },
    {
      "note": "Remove Favicons in Awesomebar to prevent HTTPS spoofing",
      "tag": "Changed",
      "is_public": true,
      "is_known_issue": false,
      "bug": 1018994
    },
    {
      "note": "Remove support for Android web runtime (WebRT)",
      "tag": "Changed",
      "is_public": true,
      "is_known_issue": false,
      "bug": 1235869
    },
    {
      "note": "Last release to support Android 2.3.x (Gingerbread)",
      "tag": "Changed",
      "is_public": true,
      "is_known_issue": false,
      "bug": 1244701
    },
    {
      "note": "\"Open multiple links\"  setting under \u201cCustomize\u201d has been renamed to \u201cTab Queue\u201d",
      "tag": "Changed",
      "is_public": true,
      "is_known_issue": false,
      "bug": 1220932
    },
    {
      "note": "Stopped data usage when Firefox is in the background and a page uses meta refresh",
      "tag": "Changed",
      "is_public": true,
      "is_known_issue": false,
      "bug": 518805
    },
    {
      "note": "WebCrypto: RSA-PSS signature support",
      "tag": "HTML5",
      "is_public": true,
      "is_known_issue": false,
      "bug": 1191936
    },
    {
      "note": "WebCrypto: PBKDF2 supports SHA-2 hash algorithms",
      "tag": "HTML5",
      "is_public": true,
      "is_known_issue": false,
      "bug": 1216109
    },
    {
      "note": "[Web platform changes][1]\r\n\r\n\r\n  [1]: https://developer.mozilla.org/en-US/Firefox/Releases/47#Changes_for_Web_developers",
      "tag": "Developer",
      "is_public": true,
      "is_known_issue": false,
      "bug": null
    }
  ],
  "text": "<p>We'd also like to extend a special thank you to all of the <a href=\"http://blog.mozilla.org/community/2016/06/04/firefox-47-new-contributors/\">new Mozillians</a> who contributed to this release of Firefox!</p>",
  "release_date": "2016-06-07",
  "slug": "firefox-for-android-47.0-release",
  "version": "47.0",
  "bug_search_url": "",
  "is_public": true,
  "system_requirements": "## Operating systems\r\n - Android 2.3\r\n - Android 4.0\r\n - Above versions\r\n\r\n## Requirements\r\n - 50 MB internal storage\r\n - 384 MB of RAM\r\n - display at least 320 pixels high and 240 pixels wide",
  "channel": "Release"
}