{
  "bug_list": "",
  "bug_search_url": "",
  "channel": "ESR",
  "created": "2015-08-06T21:48:14+00:00",
  "is_public": true,
  "modified": "2015-08-06T22:01:19+00:00",
  "notes": [
    {
      "bug": null,
      "created": "2015-08-06T21:50:17+00:00",
      "id": 786217,
      "is_public": true,
      "modified": "2015-08-06T21:50:18+00:00",
      "note": "Reference: [Firefox 38.1.0][1]\r\n\r\n\r\n  [1]: https://www.mozilla.com/en-US/firefox/38.1.0/releasenotes/",
      "sort_num": 0,
      "tag": ""
    },
    {
      "bug": null,
      "created": "2015-08-06T21:59:57+00:00",
      "id": 786218,
      "is_public": true,
      "modified": "2015-08-06T21:59:57+00:00",
      "note": "Various [security fixes][1]\r\n\r\n\r\n  [1]: https://www.mozilla.org/en-US/security/advisories/mfsa2015-78/",
      "sort_num": 1,
      "tag": "Fixed"
    }
  ],
  "product": "Firefox",
  "release_date": "2015-08-06",
  "slug": "firefox-38.1.1-esr",
  "system_requirements": "",
  "text": "",
  "title": "Firefox 38.1.1 ESR",
  "version": "38.1.1"
}