{
  "bug_list": "",
  "bug_search_url": "",
  "channel": "Release",
  "created": "2020-07-08T13:38:37.235376+00:00",
  "is_public": true,
  "modified": "2020-07-09T12:44:47.059512+00:00",
  "notes": [
    {
      "bug": null,
      "created": "2020-07-08T13:38:58.280425+00:00",
      "id": 788371,
      "is_public": true,
      "modified": "2020-07-08T13:39:17.343727+00:00",
      "note": "Reference link to [78.0.1 release notes][1]\r\n\r\n\r\n  [1]: https://www.mozilla.org/firefox/78.0.1/releasenotes/",
      "sort_num": 0,
      "tag": ""
    },
    {
      "bug": null,
      "created": "2020-07-08T13:47:27.705779+00:00",
      "id": 788373,
      "is_public": true,
      "modified": "2020-07-08T13:51:10.506677+00:00",
      "note": "[Security fix][0]\r\n\r\n[0]: https://www.mozilla.org/security/known-vulnerabilities/firefox/#firefox78.0.2",
      "sort_num": 0,
      "tag": "Fixed"
    },
    {
      "bug": 1650922,
      "created": "2020-07-08T13:49:03.399364+00:00",
      "id": 788374,
      "is_public": true,
      "modified": "2020-07-08T13:49:08.988055+00:00",
      "note": "Fixed an accessibility regression in reader mode ([bug 1650922][0])\r\n\r\n[0]: https://bugzilla.mozilla.org/1650922",
      "sort_num": 0,
      "tag": "Fixed"
    },
    {
      "bug": 1649981,
      "created": "2020-07-08T13:50:32.076151+00:00",
      "id": 788375,
      "is_public": true,
      "modified": "2020-07-08T13:50:32.075850+00:00",
      "note": "Made the address bar more resilient to data corruption in the user profile ([bug 1649981][0])\r\n\r\n[0]: https://bugzilla.mozilla.org/1649981",
      "sort_num": 0,
      "tag": "Fixed"
    },
    {
      "bug": 1650162,
      "created": "2020-07-08T17:10:44.322663+00:00",
      "id": 788376,
      "is_public": true,
      "modified": "2020-07-08T17:10:44.322475+00:00",
      "note": "Fixed a regression opening certain external applications ([bug 1650162][0])\r\n\r\n[0]: https://bugzilla.mozilla.org/1650162",
      "sort_num": 0,
      "tag": "Fixed"
    }
  ],
  "product": "Firefox",
  "release_date": "2020-07-09",
  "slug": "firefox-78.0.2-release",
  "system_requirements": "## Windows\r\n\r\n### Operating Systems (32-bit and 64-bit)\r\n - Windows 7\r\n - Windows 8\r\n - Windows 10\r\n\r\n### Recommended Hardware\r\n-  Pentium 4 or newer processor that supports SSE2\r\n-  512MB of RAM / 2GB of RAM for the 64-bit version\r\n-  200MB of hard drive space\r\n\r\n---\r\n\r\n## Mac\r\n\r\n### Operating Systems\r\n- macOS 10.9\r\n- macOS 10.10\r\n- macOS 10.11\r\n- macOS 10.12\r\n- macOS 10.13\r\n- macOS 10.14\r\n- macOS 10.15\r\n\r\n### Recommended Hardware\r\n- Macintosh computer with an Intel x86 processor\r\n- 512 MB of RAM\r\n- 200 MB hard drive space\r\n\r\n---\r\n\r\n## GNU/Linux\r\n\r\n### Software Requirements\r\n\r\n*Please note that GNU/Linux distributors may provide packages for your distribution which have different requirements.*\r\n\r\n- Firefox will not run at all without the following libraries or packages:\r\n    - GTK+ 3.14 or higher\r\n    - GLib 2.22 or higher\r\n    - Pango 1.22 or higher\r\n    - X.Org 1.0 or higher (1.7 or higher is recommended)\r\n    - libstdc++ 4.8.1 or higher\r\n    - glibc 2.17 or higher\r\n- For optimal functionality, we recommend the following libraries or packages:\r\n    - NetworkManager 0.7 or higher\r\n    - DBus 1.0 or higher\r\n    - GNOME 2.16 or higher\r\n    - PulseAudio",
  "text": "",
  "title": "Firefox 78.0.2 Release",
  "version": "78.0.2"
}