{
  "bug_list": "",
  "bug_search_url": "",
  "channel": "Release",
  "created": "2026-04-03T14:50:45.654678+00:00",
  "is_public": false,
  "modified": "2026-04-03T14:51:54.722406+00:00",
  "notes": [
    {
      "bug": null,
      "created": "2026-04-03T14:51:48.207874+00:00",
      "id": 791561,
      "is_public": true,
      "modified": "2026-04-03T14:51:48.798314+00:00",
      "note": "Reference link to [149.0 release notes][1].\r\n\r\n\r\n  [1]: https://www.firefox.com/firefox/149.0/releasenotes/",
      "progressive_rollout": false,
      "relevant_countries": [],
      "sort_num": 0,
      "tag": ""
    },
    {
      "bug": 2019983,
      "created": "2026-04-06T17:41:28.523419+00:00",
      "id": 791569,
      "is_public": true,
      "modified": "2026-04-06T17:41:29.050179+00:00",
      "note": "Introduced a new enterprise policy that allows administrators to directly manage and control AI-related features within Firefox. ([Bug 2019983][1])\r\n\r\n\r\n  [1]: https://bugzilla.mozilla.org/show_bug.cgi?id=2019983",
      "progressive_rollout": false,
      "relevant_countries": [],
      "sort_num": 0,
      "tag": "Enterprise"
    },
    {
      "bug": 2027888,
      "created": "2026-04-06T17:43:05.688752+00:00",
      "id": 791570,
      "is_public": true,
      "modified": "2026-04-06T17:43:05.688558+00:00",
      "note": "Fixed an issue where enterprise policies for the browser homepage and start page were not being applied correctly. ([Bug 2027888][1])\r\n\r\n\r\n  [1]: https://bugzilla.mozilla.org/show_bug.cgi?id=2027888",
      "progressive_rollout": false,
      "relevant_countries": [],
      "sort_num": 0,
      "tag": "Enterprise"
    },
    {
      "bug": 2022365,
      "created": "2026-04-06T17:45:20.349536+00:00",
      "id": 791571,
      "is_public": true,
      "modified": "2026-04-06T17:45:21.064120+00:00",
      "note": "Introduced a new enterprise policy that allows administrators to prevent the built-in VPN and IP protection features from being available to users. ([Bug 2022365](https://bugzilla.mozilla.org/show_bug.cgi?id=2022365))",
      "progressive_rollout": false,
      "relevant_countries": [],
      "sort_num": 0,
      "tag": "Enterprise"
    },
    {
      "bug": null,
      "created": "2026-04-03T14:53:34.419941+00:00",
      "id": 791563,
      "is_public": true,
      "modified": "2026-04-07T06:52:21.001430+00:00",
      "note": "Various [security fixes][1].\r\n\r\n\r\n  [1]: https://www.mozilla.org/security/advisories/mfsa2026-25/",
      "progressive_rollout": false,
      "relevant_countries": [],
      "sort_num": 0,
      "tag": "Fixed"
    },
    {
      "bug": 2026109,
      "created": "2026-04-06T17:31:52.827955+00:00",
      "id": 791565,
      "is_public": true,
      "modified": "2026-04-06T17:36:00.907815+00:00",
      "note": "Fixed an issue where certain parts of web pages, such as drop-down menus and specific styles, did not appear correctly when printing. ([Bug 2026109][1])\r\n\r\n\r\n  [1]: https://bugzilla.mozilla.org/show_bug.cgi?id=2026109",
      "progressive_rollout": false,
      "relevant_countries": [],
      "sort_num": 0,
      "tag": "Fixed"
    },
    {
      "bug": 2023800,
      "created": "2026-04-06T17:33:59.746977+00:00",
      "id": 791566,
      "is_public": true,
      "modified": "2026-04-06T17:36:08.578758+00:00",
      "note": "Fixed an issue where some website error pages displayed generic connection messages instead of the specific error code and description provided by the server. ([Bug 2023800)][1]\r\n\r\n\r\n  [1]: https://bugzilla.mozilla.org/show_bug.cgi?id=2023800",
      "progressive_rollout": false,
      "relevant_countries": [],
      "sort_num": 0,
      "tag": "Fixed"
    },
    {
      "bug": 2026688,
      "created": "2026-04-06T17:36:54.700943+00:00",
      "id": 791567,
      "is_public": true,
      "modified": "2026-04-06T17:36:55.425277+00:00",
      "note": "Fixed a crash that occurred when using certain security keys or WebAuthn features for two-factor authentication. ([Bug 2026688][1])\r\n\r\n\r\n  [1]: https://bugzilla.mozilla.org/show_bug.cgi?id=2026688",
      "progressive_rollout": false,
      "relevant_countries": [],
      "sort_num": 0,
      "tag": "Fixed"
    },
    {
      "bug": 2022238,
      "created": "2026-04-06T17:38:39.724375+00:00",
      "id": 791568,
      "is_public": true,
      "modified": "2026-04-06T17:38:40.254509+00:00",
      "note": "Fixed an issue on Linux where the browser toolbar could become unresponsive to mouse clicks after dragging a tab when using Wayland. ([Bug 2022238][1])\r\n\r\n\r\n  [1]: https://bugzilla.mozilla.org/show_bug.cgi?id=2022238",
      "progressive_rollout": false,
      "relevant_countries": [],
      "sort_num": 0,
      "tag": "Fixed"
    },
    {
      "bug": 2024647,
      "created": "2026-04-06T17:46:47.126799+00:00",
      "id": 791572,
      "is_public": true,
      "modified": "2026-04-06T17:46:47.681346+00:00",
      "note": "Fixed a layout issue where text inside certain graphics (SVG) appeared shifted or misaligned from its intended position. ([Bug 2024647](https://bugzilla.mozilla.org/show_bug.cgi?id=2024647))",
      "progressive_rollout": false,
      "relevant_countries": [],
      "sort_num": 0,
      "tag": "Fixed"
    },
    {
      "bug": 2023201,
      "created": "2026-04-06T17:48:37.963362+00:00",
      "id": 791573,
      "is_public": true,
      "modified": "2026-04-06T17:48:38.495256+00:00",
      "note": "Fixed an issue where the \"Send to device\" option failed to work when used from the Open Tabs section in Firefox View. ([Bug 2023201](https://bugzilla.mozilla.org/show_bug.cgi?id=2023201))",
      "progressive_rollout": false,
      "relevant_countries": [],
      "sort_num": 0,
      "tag": "Fixed"
    }
  ],
  "product": "Firefox",
  "release_date": "2026-04-07",
  "slug": "firefox-149.0.2-release",
  "system_requirements": "## Windows\r\n\r\n### Operating Systems (32-bit and 64-bit)\r\n - Windows 10 or later\r\n\r\n### Recommended Hardware\r\n-  1 gigahertz (GHz) or faster compatible processor or System on a Chip (SoC)\r\n-  1GB of RAM / 2GB of RAM for the 64-bit version\r\n-  500MB of hard drive space\r\n\r\n---\r\n\r\n## Mac\r\n\r\n### Operating Systems\r\n- macOS 10.15 or later \r\n\r\n### Recommended Hardware\r\n- Macintosh computer with an Intel x86 or Apple silicon processor\r\n- 512 MB of RAM\r\n- 200 MB hard drive space\r\n\r\n---\r\n\r\n## GNU/Linux\r\n\r\n### Software Requirements\r\n\r\n*Please note that GNU/Linux distributors may provide packages for your distribution which have different requirements.*\r\n\r\n- Firefox will not run at all without the following libraries or packages:\r\n    - glibc 2.17 or higher (glibc 2.28 or higher on arm64)\r\n    - GTK+ 3.14 or higher\r\n    - libglib 2.42 or higher\r\n    - libstdc++ 4.8.1 or higher (libstdc++ 6.0 or higher on arm64)\r\n    - X.Org 1.0 or higher (1.7 or higher is recommended)\r\n- For optimal functionality, we recommend the following libraries or packages:\r\n    - DBus 1.0 or higher\r\n    - NetworkManager 0.7 or higher\r\n    - PulseAudio",
  "text": "",
  "title": "Firefox 149.0.2 Release",
  "version": "149.0.2"
}