{
  "bug_list": "",
  "bug_search_url": "",
  "channel": "Release",
  "created": "2024-04-08T18:43:47.264456+00:00",
  "is_public": false,
  "modified": "2024-04-08T18:45:10.913489+00:00",
  "notes": [
    {
      "bug": null,
      "created": "2024-04-10T16:09:05.662131+00:00",
      "id": 790115,
      "is_public": true,
      "modified": "2024-04-10T16:09:05.662005+00:00",
      "note": "Removed the \u201cOpen in App\u201d button when Firefox is set as default PDF Viewer.",
      "progressive_rollout": false,
      "relevant_countries": [],
      "sort_num": 20,
      "tag": "Changed"
    },
    {
      "bug": null,
      "created": "2024-04-10T16:09:21.593805+00:00",
      "id": 790116,
      "is_public": true,
      "modified": "2024-04-10T16:09:21.593671+00:00",
      "note": "Firefox no longer includes the variant and extension of BCP47 in the Accept-Language header of HTTP requests for better interoperability with other browsers.",
      "progressive_rollout": false,
      "relevant_countries": [],
      "sort_num": 10,
      "tag": "Changed"
    },
    {
      "bug": null,
      "created": "2024-04-10T16:08:33.328490+00:00",
      "id": 790113,
      "is_public": true,
      "modified": "2024-04-10T16:08:33.328349+00:00",
      "note": "Firefox now recognizes the theme selection (Dark, Light, Follow Device) setting on Custom Tabs.",
      "progressive_rollout": false,
      "relevant_countries": [],
      "sort_num": 20,
      "tag": "Fixed"
    },
    {
      "bug": null,
      "created": "2024-04-10T16:08:49.917129+00:00",
      "id": 790114,
      "is_public": true,
      "modified": "2024-04-10T16:08:49.916998+00:00",
      "note": "Various improvements to the \u201cLogins and Passwords\u201d settings menu.",
      "progressive_rollout": false,
      "relevant_countries": [],
      "sort_num": 10,
      "tag": "Fixed"
    },
    {
      "bug": null,
      "created": "2024-04-08T18:46:42.018278+00:00",
      "id": 790087,
      "is_public": true,
      "modified": "2024-04-10T16:03:22.347890+00:00",
      "note": "Various [security][1] fixes.\r\n\r\n\r\n  [1]: https://www.mozilla.org/security/advisories/mfsa2024-18/",
      "progressive_rollout": false,
      "relevant_countries": [],
      "sort_num": 0,
      "tag": "Fixed"
    }
  ],
  "product": "Firefox for Android",
  "release_date": "2024-04-16",
  "slug": "firefox-for-android-125.0-release",
  "system_requirements": "## Operating systems\r\n - Android 5.0 or newer",
  "text": "",
  "title": "Firefox for Android 125.0 Release",
  "version": "125.0"
}