{
  "product": "Firefox",
  "bug_list": "",
  "title": "Firefox 33.0 Release",
  "notes": [
    {
      "note": "[OpenH264 support][1] (sandboxed)\r\n\r\n\r\n  [1]: http://andreasgal.com/2014/10/14/openh264-now-in-firefox/",
      "tag": "New",
      "sort_num": 100,
      "is_public": true,
      "is_known_issue": false,
      "bug": 948160
    },
    {
      "note": "[Improved search experience][1] through the location bar\r\n\r\n\r\n  [1]: http://msujaws.wordpress.com/2014/08/01/faster-and-snappier-searches-now-in-firefox-aurora/",
      "tag": "New",
      "sort_num": 99,
      "is_public": true,
      "is_known_issue": false,
      "bug": 982428
    },
    {
      "note": "Windows: [OMTC][1] enabled by default\r\n\r\n\r\n  [1]: https://wiki.mozilla.org/Platform/GFX/OffMainThreadCompositing\r\n",
      "tag": "New",
      "sort_num": 98,
      "is_public": true,
      "is_known_issue": false,
      "bug": 899785
    },
    {
      "note": "Slimmer and faster [JavaScript strings][1]\r\n\r\n  [1]: https://blog.mozilla.org/javascript/2014/07/21/slimmer-and-faster-javascript-strings-in-firefox/",
      "tag": "New",
      "sort_num": 98,
      "is_public": true,
      "is_known_issue": false,
      "bug": 1037871
    },
    {
      "note": "Search suggestions on the Firefox Start (about:home) and new tab (about:newtab) pages",
      "tag": "New",
      "sort_num": 98,
      "is_public": true,
      "is_known_issue": false,
      "bug": 612453
    },
    {
      "note": "Support for connecting to HTTP proxy over HTTPS",
      "tag": "New",
      "sort_num": 0,
      "is_public": true,
      "is_known_issue": false,
      "bug": 378637
    },
    {
      "note": "New CSP (Content Security Policy) backend",
      "tag": "New",
      "sort_num": 0,
      "is_public": true,
      "is_known_issue": false,
      "bug": 925004
    },
    {
      "note": "Improved reliability of the [session restoration][1]\r\n\r\n  [1]: https://dutherenverseauborddelatable.wordpress.com/2014/06/26/firefox-the-browser-that-has-your-backup/",
      "tag": "New",
      "sort_num": -1,
      "is_public": true,
      "is_known_issue": false,
      "bug": 883609
    },
    {
      "note": "Azerbaijani [az] locale added",
      "tag": "New",
      "sort_num": -100,
      "is_public": true,
      "is_known_issue": false,
      "bug": 1054497
    },
    {
      "note": "[JSD (JavaScript Debugger Service) removed][1] in favor of the Debugger interface\r\n\r\n\r\n  [1]: https://developer.mozilla.org/en-US/docs/Tools/Debugger-API",
      "tag": "Changed",
      "sort_num": 0,
      "is_public": true,
      "is_known_issue": false,
      "bug": 800200
    },
    {
      "note": "Proprietary window.crypto properties/functions removed",
      "tag": "Changed",
      "sort_num": 0,
      "is_public": true,
      "is_known_issue": false,
      "bug": 1036546
    },
    {
      "note": "[DOMMatrix][1] interface implemented\r\n\r\n\r\n  [1]: https://developer.mozilla.org/en-US/docs/Web/API/DOMMatrix",
      "tag": "HTML5",
      "sort_num": 0,
      "is_public": true,
      "is_known_issue": false,
      "bug": 1018497
    },
    {
      "note": "[@counter-style rule][1] from CSS3 Counter Styles specification implemented\r\n\r\n\r\n  [1]: http://dev.w3.org/csswg/css-counter-styles/#the-counter-style-rule",
      "tag": "HTML5",
      "sort_num": 0,
      "is_public": true,
      "is_known_issue": false,
      "bug": 966166
    },
    {
      "note": "[Cubic-bezier curves][1] editor\r\n\r\n\r\n  [1]: https://developer.mozilla.org/en-US/docs/Tools/Page_Inspector#Editing_cubic_B.C3.A9zier_curves",
      "tag": "Developer",
      "sort_num": 10,
      "is_public": true,
      "is_known_issue": false,
      "bug": 711941
    },
    {
      "note": "[Paint flashing][1] for browser content repaints\r\n\r\n\r\n  [1]: https://developer.mozilla.org/en-US/docs/Tools/Paint_Flashing_Tool",
      "tag": "Developer",
      "sort_num": 0,
      "is_public": true,
      "is_known_issue": false,
      "bug": 900692
    },
    {
      "note": "Display which elements have [listeners attached][1]\r\n\r\n\r\n  [1]: https://developer.mozilla.org/en-US/docs/Tools/Page_Inspector#Examining_event_listeners",
      "tag": "Developer",
      "sort_num": 0,
      "is_public": true,
      "is_known_issue": false,
      "bug": 736078
    },
    {
      "note": "[New sidebar][1] which displays a list of shortcuts to every @media rule in the current stylesheet\r\n\r\n\r\n  [1]: https://developer.mozilla.org/en-US/docs/Tools/Style_Editor#The_media_sidebar",
      "tag": "Developer",
      "sort_num": 0,
      "is_public": true,
      "is_known_issue": false,
      "bug": 1012806
    },
    {
      "note": "[Editable @keyframes][1] rules in the Rules section of the Inspector\r\n\r\n\r\n  [1]: https://developer.mozilla.org/en-US/docs/Tools/Page_Inspector#Editing_keyframes",
      "tag": "Developer",
      "sort_num": 0,
      "is_public": true,
      "is_known_issue": false,
      "bug": 1030889
    },
    {
      "note": "[CSS transform highlighter][1] in the style-inspector\r\n\r\n\r\n  [1]: https://developer.mozilla.org/en-US/docs/Tools/Page_Inspector#transform_visualisation",
      "tag": "Developer",
      "sort_num": 0,
      "is_public": true,
      "is_known_issue": false,
      "bug": 1014547
    },
    {
      "note": "Various <a href=\"https://www.mozilla.org/security/known-vulnerabilities/firefox.html\">security fixes</a>",
      "tag": "Fixed",
      "sort_num": 0,
      "is_public": true,
      "is_known_issue": false,
      "bug": null
    },
    {
      "note": "Fix incomplete downloads being marked as complete by detecting broken HTTP1.1 transfers ([237623][1])\r\n\r\n\r\n  [1]: https://bugzilla.mozilla.org/show_bug.cgi?id=237623",
      "tag": "Fixed",
      "sort_num": 0,
      "fixed_in_release": {
        "product": "Firefox",
        "title": "Firefox 33.0 Release",
        "version": "33.0",
        "is_public": true,
        "slug": "firefox-33.0-release",
        "channel": "Release"
      },
      "is_public": true,
      "is_known_issue": true,
      "bug": 237623
    },
    {
      "note": "PDF.js: With some images, wrong colors could show up. Affects a very small number of PDF",
      "tag": "Known",
      "sort_num": 0,
      "is_public": true,
      "is_known_issue": true,
      "bug": 1072164
    },
    {
      "note": "Some certificate errors cannot be overridden ([1042889][1])\r\n\r\n\r\n  [1]: http://bugzilla.mozilla.org/1042889",
      "tag": "Known",
      "sort_num": 0,
      "fixed_in_release": {
        "product": "Firefox",
        "title": "Firefox 33.1 Release",
        "version": "33.1",
        "is_public": true,
        "slug": "firefox-33.1-release",
        "channel": "Release"
      },
      "is_public": true,
      "is_known_issue": true,
      "bug": 1042889
    },
    {
      "note": "Windows: On some combination of hardware and drivers, the main window could be black. In this case, update your graphics drivers ([1083071][1])\r\n\r\n\r\n  [1]: https://bugzilla.mozilla.org/show_bug.cgi?id=1083071",
      "tag": "Known",
      "sort_num": 0,
      "fixed_in_release": {
        "product": "Firefox",
        "title": "Firefox 33.0.1 Release",
        "version": "33.0.1",
        "is_public": true,
        "slug": "firefox-33.0.1-release",
        "channel": "Release"
      },
      "is_public": true,
      "is_known_issue": true,
      "bug": 1083071
    },
    {
      "note": "Windows: With Avast HTTPS scanning enabled, Firefox will not close correctly ([1087674][1])\r\n\r\n\r\n  [1]: https://bugzilla.mozilla.org/show_bug.cgi?id=1087674",
      "tag": "Known",
      "sort_num": 0,
      "fixed_in_release": {
        "product": "Firefox",
        "title": "Firefox 33.1 Release",
        "version": "33.1",
        "is_public": true,
        "slug": "firefox-33.1-release",
        "channel": "Release"
      },
      "is_public": true,
      "is_known_issue": true,
      "bug": 1087674
    },
    {
      "note": "Windows: Interface may be slow when typing or selecting text ([1089183][1])\r\n\r\n\r\n  [1]: https://bugzilla.mozilla.org/show_bug.cgi?id=1089183",
      "tag": "Known",
      "sort_num": 0,
      "is_public": true,
      "is_known_issue": true,
      "bug": 1087674
    }
  ],
  "text": "<p>We'd also like to extend a special thank you to all of the <a href=\"https://blog.mozilla.org/community/2014/10/09/firefox-33-new-contributors/\">new Mozillians</a> who contributed to this release of Firefox!</p>",
  "release_date": "2014-10-13",
  "slug": "firefox-33.0-release",
  "version": "33.0",
  "bug_search_url": "",
  "is_public": true,
  "system_requirements": "## Windows\r\n\r\n### Operating Systems\r\n - Windows XP SP2\r\n - Windows Server 2003 SP1\r\n - Windows Vista\r\n - Windows 7\r\n - Windows 8\r\n\r\n*Please note that while the 32-bit and 64-bit versions of Windows Vista and Windows 7 can be used to run Firefox 33, only 32-bit builds of Firefox 33 are supported at this time.*\r\n\r\n### Recommended Hardware\r\n-  Pentium 4 or newer processor that supports SSE2\r\n-  512MB of RAM\r\n-  200MB of hard drive space\r\n\r\n---\r\n\r\n## Mac\r\n\r\n### Operating Systems\r\n- Mac OS X 10.6\r\n- Mac OS X 10.7\r\n- Mac OS X 10.8\r\n- Mac OS X 10.9\r\n\r\n### Recommended Hardware\r\n- Macintosh computer with an Intel x86 processor\r\n- 512 MB of RAM\r\n- 200 MB hard drive space\r\n\r\n---\r\n\r\n## GNU/Linux\r\n\r\n### Software Requirements\r\n\r\n*Please note that GNU/Linux distributors may provide packages for your distribution which have different requirements.*\r\n\r\n- Firefox will not run at all without the following libraries or packages:\r\n    - GTK+ 2.18 or higher\r\n    - GLib 2.22 or higher\r\n    - Pango 1.14 or higher\r\n    - X.Org 1.0 or higher (1.7 or higher is recommended)\r\n    - libstdc++ 4.3 or higher\r\n- For optimal functionality, we recommend the following libraries or packages:\r\n    - NetworkManager 0.7 or higher\r\n    - DBus 1.0 or higher\r\n    - HAL 0.5.8 or higher\r\n    - GNOME 2.16 or higher",
  "channel": "Release"
}