{
  "bug_list": "",
  "bug_search_url": "",
  "channel": "Release",
  "created": "2014-11-04T14:29:56+00:00",
  "is_public": true,
  "modified": "2014-11-10T13:40:21+00:00",
  "notes": [
    {
      "bug": 1069300,
      "created": "2014-11-04T14:44:49+00:00",
      "id": 785770,
      "is_public": true,
      "modified": "2014-11-14T22:22:08+00:00",
      "note": "[Forget Button][1] added\r\n\r\n\r\n  [1]: https://support.mozilla.org/kb/forget-button-quickly-delete-your-browsing-history",
      "sort_num": 1000,
      "tag": "New"
    },
    {
      "bug": 1030832,
      "created": "2014-08-28T04:48:13+00:00",
      "id": 785692,
      "is_public": true,
      "modified": "2014-11-14T22:22:08+00:00",
      "note": "[Enhanced Tiles][1]\r\n\r\n\r\n  [1]: https://www.mozilla.org/en-US/firefox/tiles/",
      "sort_num": 100,
      "tag": "New"
    },
    {
      "bug": 1061736,
      "created": "2014-11-04T14:34:41+00:00",
      "id": 785769,
      "is_public": true,
      "modified": "2014-11-14T22:22:08+00:00",
      "note": "Adding DuckDuckGo as a search option",
      "sort_num": 0,
      "tag": "New"
    },
    {
      "bug": 1071187,
      "created": "2014-11-04T14:32:50+00:00",
      "id": 785768,
      "is_public": true,
      "modified": "2014-11-14T22:22:08+00:00",
      "note": "Privacy tour introduced",
      "sort_num": 0,
      "tag": "New"
    },
    {
      "bug": 1087674,
      "created": "2014-10-29T16:05:46+00:00",
      "id": 785767,
      "is_public": true,
      "modified": "2014-11-14T22:22:08+00:00",
      "note": "Windows: Interface may be slow when typing or selecting text ([1089183][1])\r\n\r\n\r\n  [1]: https://bugzilla.mozilla.org/show_bug.cgi?id=1089183",
      "sort_num": 0,
      "tag": "Known"
    },
    {
      "bug": null,
      "created": "2014-11-10T13:04:52+00:00",
      "id": 785780,
      "is_public": true,
      "modified": "2014-11-14T22:22:08+00:00",
      "note": "Windows: On some combination of hardware and drivers, some flickering can happen\r\n",
      "sort_num": 0,
      "tag": "Known"
    },
    {
      "bug": 1072164,
      "created": "2014-10-07T02:27:18+00:00",
      "id": 785747,
      "is_public": true,
      "modified": "2014-11-14T22:22:08+00:00",
      "note": "PDF.js: With some images, wrong colors could show up. Affects a very small number of PDF",
      "sort_num": 0,
      "tag": "Known"
    }
  ],
  "product": "Firefox",
  "release_date": "2014-11-10",
  "slug": "firefox-33.1-release",
  "system_requirements": "## Windows\r\n\r\n### Operating Systems\r\n - Windows XP SP2\r\n - Windows Server 2003 SP1\r\n - Windows Vista\r\n - Windows 7\r\n - Windows 8\r\n\r\n*Please note that while the 32-bit and 64-bit versions of Windows Vista and Windows 7 can be used to run Firefox 33, only 32-bit builds of Firefox 33 are supported at this time.*\r\n\r\n### Recommended Hardware\r\n-  Pentium 4 or newer processor that supports SSE2\r\n-  512MB of RAM\r\n-  200MB of hard drive space\r\n\r\n---\r\n\r\n## Mac\r\n\r\n### Operating Systems\r\n- Mac OS X 10.6\r\n- Mac OS X 10.7\r\n- Mac OS X 10.8\r\n- Mac OS X 10.9\r\n\r\n### Recommended Hardware\r\n- Macintosh computer with an Intel x86 processor\r\n- 512 MB of RAM\r\n- 200 MB hard drive space\r\n\r\n---\r\n\r\n## GNU/Linux\r\n\r\n### Software Requirements\r\n\r\n*Please note that GNU/Linux distributors may provide packages for your distribution which have different requirements.*\r\n\r\n- Firefox will not run at all without the following libraries or packages:\r\n    - GTK+ 2.18 or higher\r\n    - GLib 2.22 or higher\r\n    - Pango 1.14 or higher\r\n    - X.Org 1.0 or higher (1.7 or higher is recommended)\r\n    - libstdc++ 4.3 or higher\r\n- For optimal functionality, we recommend the following libraries or packages:\r\n    - NetworkManager 0.7 or higher\r\n    - DBus 1.0 or higher\r\n    - HAL 0.5.8 or higher\r\n    - GNOME 2.16 or higher",
  "text": "<p>We'd also like to extend a special thank you to all of the <a href=\"https://blog.mozilla.org/community/2014/10/09/firefox-33-new-contributors/\">new Mozillians</a> who contributed to this release of Firefox!</p>",
  "title": "Firefox 33.1 Release",
  "version": "33.1"
}