{
  "bug_list": "",
  "bug_search_url": "",
  "channel": "Nightly",
  "created": "2019-09-02T12:06:15.618961+00:00",
  "is_public": true,
  "modified": "2019-09-02T13:36:27.572545+00:00",
  "notes": [
    {
      "bug": 1423714,
      "created": "2019-09-23T07:52:25.512118+00:00",
      "id": 788143,
      "is_public": true,
      "modified": "2019-10-21T09:54:02.460670+00:00",
      "note": "Passwords can be imported from Chrome on macOS in addition to existing support for Windows",
      "sort_num": 0,
      "tag": "New"
    },
    {
      "bug": 1580094,
      "created": "2019-09-23T11:04:51.518080+00:00",
      "id": 788144,
      "is_public": true,
      "modified": "2019-10-21T11:43:51.983754+00:00",
      "note": "Locale added: Catalan (Valencia) (ca-valencia)",
      "sort_num": 0,
      "tag": "New"
    },
    {
      "bug": 158968,
      "created": "2019-10-07T18:07:46.654305+00:00",
      "id": 788151,
      "is_public": true,
      "modified": "2019-10-21T11:42:59.607318+00:00",
      "note": "Firefox has a new command line parameter, `--kiosk`, that opens Firefox in fullscreen mode",
      "sort_num": 0,
      "tag": "New"
    },
    {
      "bug": 1579270,
      "created": "2019-10-15T08:25:14.871109+00:00",
      "id": 788156,
      "is_public": true,
      "modified": "2019-10-21T09:53:58.709569+00:00",
      "note": "<!-- Nightly Only --> Disabled TLS 1.0 and 1.1 by default on the Nightly channel",
      "sort_num": 0,
      "tag": "Changed"
    },
    {
      "bug": null,
      "created": "2019-10-21T11:52:35.536661+00:00",
      "id": 788185,
      "is_public": true,
      "modified": "2019-10-21T11:52:35.536454+00:00",
      "note": "[Subgrid][1] greatly enhances the utility and flexibility of grid layouts by allowing the grid of a child to use the tracks defined on the parent. In addition, the DevTools grid inspector has been improved to support subgrid.\r\n\r\n\r\n  [1]: https://developer.mozilla.org/en-US/docs/Web/CSS/CSS_Grid_Layout/Subgrid",
      "sort_num": 0,
      "tag": "HTML5"
    },
    {
      "bug": 1403051,
      "created": "2019-10-08T11:38:13.022506+00:00",
      "id": 788152,
      "is_public": true,
      "modified": "2019-10-21T11:42:24.904689+00:00",
      "note": "Using the [new server-timing information][1] in DevTools' Network panel, developers can analyze the server-related timings in context of other request and response details.\r\n\r\n\r\n  [1]: https://developer.mozilla.org/en-US/docs/Tools/Network_Monitor/request_details#Timings",
      "sort_num": 0,
      "tag": "Developer"
    }
  ],
  "product": "Firefox",
  "release_date": "2019-09-02",
  "slug": "firefox-71.0a1-nightly",
  "system_requirements": "## Windows\r\n\r\n### Operating Systems (32-bit and 64-bit)\r\n - Windows 7\r\n - Windows 8\r\n - Windows 10\r\n\r\n### Recommended Hardware\r\n-  Pentium 4 or newer processor that supports SSE2\r\n-  512MB of RAM / 2GB of RAM for the 64-bit version\r\n-  200MB of hard drive space\r\n\r\n---\r\n\r\n## Mac\r\n\r\n### Operating Systems\r\n- macOS 10.9\r\n- macOS 10.10\r\n- macOS 10.11\r\n- macOS 10.12\r\n- macOS 10.13\r\n- macOS 10.14\r\n\r\n### Recommended Hardware\r\n- Macintosh computer with an Intel x86 processor\r\n- 512 MB of RAM\r\n- 200 MB hard drive space\r\n\r\n---\r\n\r\n## GNU/Linux\r\n\r\n### Software Requirements\r\n\r\n*Please note that GNU/Linux distributors may provide packages for your distribution which have different requirements.*\r\n\r\n- Firefox will not run at all without the following libraries or packages:\r\n    - GTK+ 3.4 or higher\r\n    - GLib 2.22 or higher\r\n    - Pango 1.22 or higher\r\n    - X.Org 1.0 or higher (1.7 or higher is recommended)\r\n    - libstdc++ 4.6.1 or higher\r\n- For optimal functionality, we recommend the following libraries or packages:\r\n    - NetworkManager 0.7 or higher\r\n    - DBus 1.0 or higher\r\n    - GNOME 2.16 or higher\r\n    - PulseAudio",
  "text": "Firefox Nightly gets updated every day and as a consequence, the release notes for the Nightly channel are updated continuously to reflect features that have reached sufficient maturity to benefit from community feedback and bug reports. \r\n\r\n**Warning: Features listed here may or may *not* make a final release of Firefox.**\r\n\r\nIn addition to these release notes, you can follow ongoing development on our [@FirefoxNightly][1] Twitter account as well as read our [Nightly Blog][2].\r\n\r\n[1]: https://twitter.com/FirefoxNightly\r\n[2]: https://blog.nightly.mozilla.org",
  "title": "Firefox 71.0a1 Nightly",
  "version": "71.0a1"
}